university_ranking_scraper/__init__.py
university_ranking_scraper/__main__.py
university_ranking_scraper/constant.py
us_news/__init__.py
us_news/__main__.py
us_news-0.0.8.dist-info/METADATA
us_news-0.0.8.dist-info/WHEEL
us_news-0.0.8.dist-info/top_level.txt
us_news-0.0.8.dist-info/RECORD
