Metadata-Version: 2.1
Name: us-news
Version: 0.0.8
Summary: DEPRECATED – Use university_ranking_scraper instead
Home-page: https://github.com/lowweihong/university_ranking_scraper
Author: Low Wei Hong
Author-email: M140042@e.ntu.edu.sg
License: UNKNOWN
Keywords: university_rankings,usnews,times_higher_education,qs
Platform: UNKNOWN
Classifier: Programming Language :: Python :: 3
Requires-Dist: pandas
Requires-Dist: httpx
Requires-Dist: lxml
